hibp.py
hibp/__init__.py
hibp/example.py
hibp/hibp.py
hibp-0.0.5.dist-info/DESCRIPTION.rst
hibp-0.0.5.dist-info/METADATA
hibp-0.0.5.dist-info/RECORD
hibp-0.0.5.dist-info/WHEEL
hibp-0.0.5.dist-info/metadata.json
hibp-0.0.5.dist-info/top_level.txt
