Metadata-Version: 2.0
Name: hibp
Version: 0.0.5
Summary: A Python interface to the Have I Been Pwned API
Home-page: https://github.com/pegasos1/haveibeenpwned
Author: pegasos1
Author-email: sgrangan01@gmail.com
License: Apache 2.0
Keywords: security breach api pwned hack
Platform: UNKNOWN
Classifier: Development Status :: 3 - Alpha
Classifier: Intended Audience :: Developers
Classifier: Topic :: Security
Classifier: License :: OSI Approved :: Apache Software License
Classifier: Programming Language :: Python :: 3
Classifier: Programming Language :: Python :: 3.3
Classifier: Programming Language :: Python :: 3.4
Classifier: Programming Language :: Python :: 3.5
Requires-Dist: gevent
Requires-Dist: requests
